LICENCE
README.md
setup.py
credicom_rpa/FilaRepository.py
credicom_rpa/SqlBase.py
credicom_rpa/__init__.py
credicom_rpa/cryptographys.py
credicom_rpa/orchestrator.py
credicom_rpa/pyUtils.py
credicom_rpa/sisbrDesktop.py
sisbr_credicom.egg-info/PKG-INFO
sisbr_credicom.egg-info/SOURCES.txt
sisbr_credicom.egg-info/dependency_links.txt
sisbr_credicom.egg-info/requires.txt
sisbr_credicom.egg-info/top_level.txt