Metadata-Version: 2.1
Name: sisbr-credicom
Version: 0.0.6
Summary: função login dos sistemas sicoob
Author: Gabriel Moreno
Author-email: gabrielgoncalvesmoreno@credicom.com.br
License: MIT License
Keywords: sisbr
License-File: LICENCE
Requires-Dist: botcity-framework-base
Requires-Dist: cryptocode
Requires-Dist: pyodbc
